csvprocessor/__init__.py
csvprocessor/csvtodb.py
csv_processor-1.0.0.dist-info/LICENSE
csv_processor-1.0.0.dist-info/METADATA
csv_processor-1.0.0.dist-info/WHEEL
csv_processor-1.0.0.dist-info/top_level.txt
csv_processor-1.0.0.dist-info/RECORD
