Metadata-Version: 2.1
Name: csv-processor
Version: 1.0.0
Summary: Python 3+ CSV file processor
Home-page: UNKNOWN
Author: Harvard90873
Author-email: harvard90873@gmail.com
License: MIT
Platform: UNKNOWN
Classifier: License :: OSI Approved :: MIT License
Classifier: Programming Language :: Python :: 3.9
Classifier: Programming Language :: Python :: 3
Requires-Dist: and-or-not
Requires-Dist: data-structures3x
Requires-Dist: python-algorithms-3x
Requires-Dist: spell-checker
Requires-Dist: termcolor
Requires-Dist: word-scramble
